Workbook

Sheet DashBoard
B1: Budget DashBoard | W1: r
A4: Month & Year: | B4: 46204 | E4: ="Savings Rate: "&TEXT(IFERROR(C29/C12,0),"0.0%") -> Savings Rate: 65.9% | G4: ="Remaining Budget: "&TEXT(D26-C26,"$#,##0.00") -> Remaining Budget: $1,076.93 | K4: ="Net Savings: " &TEXT(C29,"$#,##0.00") -> Net Savings: $1,551.49 | O4: ="Monthly Income: " &TEXT(C12,"$#,##0.00") -> Monthly Income: $2,354.56 | T4: ="Monthly Expenses: " &TEXT(C26,"$#,##0.00") -> Monthly Expenses: $803.07
A7: ="Breakdown - " & TEXT(B4, "mmmm yyyy") -> Breakdown - July 2026 | I7: ="Summary - " & TEXT(B4, "mmmm yyyy") -> Summary - July 2026
A9: Income | C9: Actual | D9: Budget | E9: Variance | F9: % Completed | G9: Status
A10: Salary Income | C10: =SUMIFS(Tracker[[Amount ]],Tracker[Type],A10,Tracker[Date],">="&EOMONTH($B$4,-1)+1,Tracker[Date],"<="&EOMONTH($B$4,0)) -> 2347.51 | D10: =SUMIFS(Budget[Budget],Budget[Category],$A10,Budget[Date],$B$4) -> 3000 | E10: =C10-D10 -> -652.49 | F10: =IFERROR(C10/D10,0) -> 0.78250333 | G10: =IF(C10>=D10,"Goal Met", IF(C10>=D10*0.9,"Near Goal","Below Goal")) -> Below Goal | M10: {=_xlfn._xlws.SORT(_xlfn._xlws.FILTER(_xlfn.CHOOSECOLS(A15:C25, 1, 3), C15:C25), 2, -1)} -> Utilities | N10: 200
A11: Other Income | C11: =SUMIFS(Tracker[[Amount ]],Tracker[Type],A11,Tracker[Date],">="&EOMONTH($B$4,-1)+1,Tracker[Date],"<="&EOMONTH($B$4,0)) -> 7.05 | D11: =SUMIFS(Budget[Budget],Budget[Category],$A11,Budget[Date],$B$4) -> 20 | E11: =C11-D11 -> -12.95 | F11: =IFERROR(C11/D11,0) -> 0.3525 | G11: =IF(C11>=D11,"Goal Met", IF(C11>=D11*0.9,"Near Goal","Below Goal")) -> Below Goal | M11: Leisure | N11: 131
A12: Total | C12: =SUM(C10:C11) -> 2354.56 | D12: =SUM(D10:D11) -> 3020 | E12: =SUM(E10:E11) -> -665.44 | F12: =IFERROR(C12/D12,0) -> 0.77965563 | M12: Debt | N12: 130
M13: Insurance | N13: 120
A14: Expenses | C14: Actual | D14: Budget | E14: Variance | F14: % Used | G14: Status | M14: Housing | N14: 100
A15: Housing | C15: =SUMIFS(Tracker[[Amount ]],Tracker[Category],A15,Tracker[Date],">="&EOMONTH($B$4,-1)+1,Tracker[Date],"<="&EOMONTH($B$4,0)) -> 100 | D15: =SUMIFS(Budget[Budget],Budget[Category],$A15,Budget[Date],$B$4) -> 0 | E15: =D15-C15 -> -100 | F15: =IFERROR(C15/D15,0) -> 0 | G15: =IF(C15>D15,"Over Budget", IF(C15>=D15*0.9,"On Budget","Under Budget")) -> Over Budget | M15: Subscriptions | N15: 43.98
A16: Utilities | C16: =SUMIFS(Tracker[[Amount ]],Tracker[Category],A16,Tracker[Date],">="&EOMONTH($B$4,-1)+1,Tracker[Date],"<="&EOMONTH($B$4,0)) -> 200 | D16: =SUMIFS(Budget[Budget],Budget[Category],$A16,Budget[Date],$B$4) -> 0 | E16: =D16-C16 -> -200 | F16: =IFERROR(C16/D16,0) -> 0 | G16: =IF(C16>D16,"Over Budget", IF(C16>=D16*0.9,"On Budget","Under Budget")) -> Over Budget | M16: Miscellaneous | N16: 34.56
A17: Transportation | C17: =SUMIFS(Tracker[[Amount ]],Tracker[Category],A17,Tracker[Date],">="&EOMONTH($B$4,-1)+1,Tracker[Date],"<="&EOMONTH($B$4,0)) -> 26.54 | D17: =SUMIFS(Budget[Budget],Budget[Category],$A17,Budget[Date],$B$4) -> 500 | E17: =D17-C17 -> 473.46 | F17: =IFERROR(C17/D17,0) -> 0.05308 | G17: =IF(C17>D17,"Over Budget", IF(C17>=D17*0.9,"On Budget","Under Budget")) -> Under Budget | M17: Transportation | N17: 26.54
A18: Insurance | C18: =SUMIFS(Tracker[[Amount ]],Tracker[Category],A18,Tracker[Date],">="&EOMONTH($B$4,-1)+1,Tracker[Date],"<="&EOMONTH($B$4,0)) -> 120 | D18: =SUMIFS(Budget[Budget],Budget[Category],$A18,Budget[Date],$B$4) -> 120 | E18: =D18-C18 -> 0 | F18: =IFERROR(C18/D18,0) -> 1 | G18: =IF(C18>D18,"Over Budget", IF(C18>=D18*0.9,"On Budget","Under Budget")) -> On Budget | M18: Groceries | N18: 6.99
A19: Groceries | C19: =SUMIFS(Tracker[[Amount ]],Tracker[Category],A19,Tracker[Date],">="&EOMONTH($B$4,-1)+1,Tracker[Date],"<="&EOMONTH($B$4,0)) -> 6.99 | D19: =SUMIFS(Budget[Budget],Budget[Category],$A19,Budget[Date],$B$4) -> 100 | E19: =D19-C19 -> 93.01 | F19: =IFERROR(C19/D19,0) -> 0.0699 | G19: =IF(C19>D19,"Over Budget", IF(C19>=D19*0.9,"On Budget","Under Budget")) -> Under Budget | M19: Healthcare | N19: 5
A20: Leisure | C20: =SUMIFS(Tracker[[Amount ]],Tracker[Category],A20,Tracker[Date],">="&EOMONTH($B$4,-1)+1,Tracker[Date],"<="&EOMONTH($B$4,0)) -> 131 | D20: =SUMIFS(Budget[Budget],Budget[Category],$A20,Budget[Date],$B$4) -> 200 | E20: =D20-C20 -> 69 | F20: =IFERROR(C20/D20,0) -> 0.655 | G20: =IF(C20>D20,"Over Budget", IF(C20>=D20*0.9,"On Budget","Under Budget")) -> Under Budget | M20: Education | N20: 5
A21: Healthcare | C21: =SUMIFS(Tracker[[Amount ]],Tracker[Category],A21,Tracker[Date],">="&EOMONTH($B$4,-1)+1,Tracker[Date],"<="&EOMONTH($B$4,0)) -> 5 | D21: =SUMIFS(Budget[Budget],Budget[Category],$A21,Budget[Date],$B$4) -> 50 | E21: =D21-C21 -> 45 | F21: =IFERROR(C21/D21,0) -> 0.1 | G21: =IF(C21>D21,"Over Budget", IF(C21>=D21*0.9,"On Budget","Under Budget")) -> Under Budget | M21: Total | N21: =SUM(N10:N20) -> 803.07
A22: Debt | C22: =SUMIFS(Tracker[[Amount ]],Tracker[Category],A22,Tracker[Date],">="&EOMONTH($B$4,-1)+1,Tracker[Date],"<="&EOMONTH($B$4,0)) -> 130 | D22: =SUMIFS(Budget[Budget],Budget[Category],$A22,Budget[Date],$B$4) -> 800 | E22: =D22-C22 -> 670 | F22: =IFERROR(C22/D22,0) -> 0.1625 | G22: =IF(C22>D22,"Over Budget", IF(C22>=D22*0.9,"On Budget","Under Budget")) -> Under Budget
A23: Education | C23: =SUMIFS(Tracker[[Amount ]],Tracker[Category],A23,Tracker[Date],">="&EOMONTH($B$4,-1)+1,Tracker[Date],"<="&EOMONTH($B$4,0)) -> 5 | D23: =SUMIFS(Budget[Budget],Budget[Category],$A23,Budget[Date],$B$4) -> 20 | E23: =D23-C23 -> 15 | F23: =IFERROR(C23/D23,0) -> 0.25 | G23: =IF(C23>D23,"Over Budget", IF(C23>=D23*0.9,"On Budget","Under Budget")) -> Under Budget
A24: Subscriptions | C24: =SUMIFS( Subscriptions[Monthly Cost], Subscriptions[Period Renewal Date],">="&EOMONTH($B$4,-1)+1, Subscriptions[Period Renewal Date],"<"&EOMONTH($B$4,0)+1 ) -> 43.98 | D24: =SUMIFS(Budget[Budget],Budget[Category],$A24,Budget[Date],$B$4) -> 40 | E24: =D24-C24 -> -3.98 | F24: =IFERROR(C24/D24,0) -> 1.0995 | G24: =IF(C24>D24,"Over Budget", IF(C24>=D24*0.9,"On Budget","Under Budget")) -> Over Budget
A25: Miscellaneous | C25: =SUMIFS(Tracker[[Amount ]],Tracker[Category],A25,Tracker[Date],">="&EOMONTH($B$4,-1)+1,Tracker[Date],"<="&EOMONTH($B$4,0)) -> 34.56 | D25: =SUMIFS(Budget[Budget],Budget[Category],$A25,Budget[Date],$B$4) -> 50 | E25: =D25-C25 -> 15.44 | F25: =IFERROR(C25/D25,0) -> 0.6912 | G25: =IF(C25>D25,"Over Budget", IF(C25>=D25*0.9,"On Budget","Under Budget")) -> Under Budget
A26: Total | C26: =SUM(C15:C25) -> 803.07 | D26: =SUM(D15:D25) -> 1880 | E26: =SUM(E15:E25) -> 1076.93 | F26: =IFERROR(C26/D26,0) -> 0.42716489
U27: =Budget!E2 -> Debt Paydown | V27: =Budget!F2 -> 0.6
A28: Savings | C28: Actual | D28: Budget | E28: Variance | F28: % Saved | G28: Status | U28: =Budget!E3 -> Emeregency Fund | V28: =Budget!F3 -> 0.2
A29: Actual Savings | C29: =MAX(C12-C26,0) -> 1551.49 | D29: =SUMIFS(Budget[Budget],Budget[Category],$A29,Budget[Date],$B$4) -> 500 | E29: =C29-D29 -> 1051.49 | F29: =IFERROR(C29/D29,0) -> 3.10298 | G29: =IF(C29>=D29,"Goal Met", IF(C29>=D29*0.9,"Near Goal","Below Goal")) -> Goal Met | U29: =Budget!E4 -> Investments | V29: =Budget!F4 -> 0.2
A30: Debt Paydown | C30: =$C$29*Budget!F2 -> 930.894 | D30: =$D$29*Budget!F2 -> 300 | E30: =C30-D30 -> 630.894 | F30: =IFERROR(C30/D30,0) -> 3.10298 | G30: =IF(C30>=D30,"Goal Met", IF(C30>=D30*0.9,"Near Goal","Below Goal")) -> Goal Met
A31: Emeregency Fund | C31: =$C$29*Budget!F3 -> 310.298 | D31: =$D$29*Budget!F3 -> 100 | E31: =C31-D31 -> 210.298 | F31: =IFERROR(C31/D31,0) -> 3.10298 | G31: =IF(C31>=D31,"Goal Met", IF(C31>=D31*0.9,"Near Goal","Below Goal")) -> Goal Met
A32: Investments | C32: =$C$29*Budget!F4 -> 310.298 | D32: =$D$29*Budget!F4 -> 100 | E32: =C32-D32 -> 210.298 | F32: =IFERROR(C32/D32,0) -> 3.10298 | G32: =IF(C32>=D32,"Goal Met", IF(C32>=D32*0.9,"Near Goal","Below Goal")) -> Goal Met
U33: {=_xlfn._xlws.SORT(_xlfn.CHOOSECOLS(A30:C32,1,3),2,-1)} -> Debt Paydown | V33: 930.894
U34: Emeregency Fund | V34: 310.298
U35: Investments | V35: 310.298
U36: Total | V36: =SUM(V33:V35) -> 1551.49

Sheet Transactions
A1: Date | B1: Type | C1: Description | D1: Category | E1: Amount
A2: 46221 | B2: Expense | C2: Parking Ticket | D2: Miscellaneous | E2: 10
A3: 46221 | B3: Expense | C3: Gas Money | D3: Transportation | E3: 5
A4: 46222 | B4: Salary Income | C4: PayCheck | E4: 60
A5: 46222 | B5: Other Income | C5: Sold Clothing Item | E5: 7.05
A6: 46222 | B6: Expense | C6: Drinks | D6: Leisure | E6: 36
A7: 46223 | B7: Salary Income | C7: Pay Check | E7: 1400
A8: 46223 | B8: Expense | C8: Parking Ticket | D8: Transportation | E8: 13
A9: 46223 | B9: Expense | C9: Lockes Coupons | D9: Miscellaneous | E9: 20
A10: 46224 | B10: Expense | C10: Milk | D10: Groceries | E10: 6.99
A11: 46224 | B11: Expense | C11: Celius | D11: Miscellaneous | E11: 4.56
A12: 46224 | B12: Expense | C12: Gas money for lex | D12: Transportation | E12: 8.54
A13: 46225 | B13: Salary Income | C13: PNC Investments | E13: 887.51
A14: 46227 | B14: Expense | C14: Tequilla cowboy | D14: Leisure | E14: 90
A15: 46227 | B15: Expense | C15: Test | D15: Healthcare | E15: 5
A16: 46227 | B16: Expense | C16: Insurance | D16: Insurance | E16: 120
A17: 46227 | B17: Expense | C17: Student loan payment | D17: Debt | E17: 130
A18: 46227 | B18: Expense | C18: Movie | D18: Leisure | E18: 5
A19: 46227 | B19: Expense | C19: audible | D19: Education | E19: 5
A20: 46227 | B20: Expense | C20: rent | D20: Housing | E20: 100
A21: 46227 | B21: Expense | C21: electric | D21: Utilities | E21: 200

Sheet Budget
A1: Date | B1: Category | C1: Budget | E1: Account Allocation Rates | F1: %
A2: 46204 | B2: Salary Income | C2: 3000 | E2: =DashBoard!A30 -> Debt Paydown | F2: 0.6
A3: 46204 | B3: Other Income | C3: 20 | E3: =DashBoard!A31 -> Emeregency Fund | F3: 0.2
A4: 46204 | B4: Housing | C4: 0 | E4: =DashBoard!A32 -> Investments | F4: 0.2
A5: 46204 | B5: Utilities | C5: 0
A6: 46204 | B6: Transportation | C6: 500
A7: 46204 | B7: Insurance | C7: 120
A8: 46204 | B8: Groceries | C8: 100
A9: 46204 | B9: Leisure | C9: 200
A10: 46204 | B10: Healthcare | C10: 50
A11: 46204 | B11: Debt | C11: 800
A12: 46204 | B12: Education | C12: 20
A13: 46204 | B13: Subscriptions | C13: 40
A14: 46204 | B14: Miscellaneous | C14: 50
A15: 46204 | B15: Actual Savings | C15: 500
A16: 46235 | B16: Salary Income
A17: 46235 | B17: Other Income
A18: 46235 | B18: Housing
A19: 46235 | B19: Utilities
A20: 46235 | B20: Transportation
A21: 46235 | B21: Insurance
A22: 46235 | B22: Groceries
A23: 46235 | B23: Leisure
A24: 46235 | B24: Healthcare
A25: 46235 | B25: Debt
A26: 46235 | B26: Education
A27: 46235 | B27: Subscriptions
... A29: 46235 | B29: Actual Savings

Sheet Subscriptions
A1: Service | B1: Category | C1: Monthly Cost | D1: Renewal Frequency | E1: Renewal Date | F1: Next Renewal | G1: Period Renewal Date | H1: Notes
A2: Chat Gpt Plus | B2: Education | C2: 21.15 | D2: Monthly | E2: 10 | F2: =IF( DATE(YEAR(TODAY()),MONTH(TODAY()),E2)>=TODAY(), DATE(YEAR(TODAY()),MONTH(TODAY()),E2), EDATE(DATE(YEAR(TODAY()),MONTH(TODAY()),E2),1) ) -> 46244 | G2: =IF(Subscriptions[[#This Row],[Renewal Frequency]]="Monthly", DATE( YEAR(DashBoard!$B$4), MONTH(DashBoard!$B$4), MIN(VALUE(Subscriptions[[#This Row],[Renewal Date]]),DAY(EOMONTH(DashBoard!$B$4,0))) ), DATE( YEAR(DashBoard!$B$4), MONTH(Subscriptions[[#This Row],[Renewal Date]]), DAY(Subscriptions[[#This Row],[Renewal Date]]) ) ) -> 46213
A3: Icloud+ | B3: Entertainment | C3: 2.99 | D3: Monthly | E3: 21 | F3: =IF( DATE(YEAR(TODAY()),MONTH(TODAY()),E3)>=TODAY(), DATE(YEAR(TODAY()),MONTH(TODAY()),E3), EDATE(DATE(YEAR(TODAY()),MONTH(TODAY()),E3),1) ) -> 46255 | G3: =IF(Subscriptions[[#This Row],[Renewal Frequency]]="Monthly", DATE( YEAR(DashBoard!$B$4), MONTH(DashBoard!$B$4), MIN(Subscriptions[[#This Row],[Renewal Date]],DAY(EOMONTH(DashBoard!$B$4,0))) ), DATE( YEAR(DashBoard!$B$4), MONTH(Subscriptions[[#This Row],[Renewal Date]]), DAY(Subscriptions[[#This Row],[Renewal Date]]) ) ) -> 46224
A4: Audible | B4: Education | C4: 15.85 | D4: Monthly | E4: 29 | F4: =IF( DATE(YEAR(TODAY()),MONTH(TODAY()),E4)>=TODAY(), DATE(YEAR(TODAY()),MONTH(TODAY()),E4), EDATE(DATE(YEAR(TODAY()),MONTH(TODAY()),E4),1) ) -> 46232 | G4: =IF(Subscriptions[[#This Row],[Renewal Frequency]]="Monthly", DATE( YEAR(DashBoard!$B$4), MONTH(DashBoard!$B$4), MIN(Subscriptions[[#This Row],[Renewal Date]],DAY(EOMONTH(DashBoard!$B$4,0))) ), DATE( YEAR(DashBoard!$B$4), MONTH(Subscriptions[[#This Row],[Renewal Date]]), DAY(Subscriptions[[#This Row],[Renewal Date]]) ) ) -> 46232
A5: WSJ | B5: Education | C5: 3.99 | D5: Monthly | E5: 1 | F5: =IF( DATE(YEAR(TODAY()),MONTH(TODAY()),E5)>=TODAY(), DATE(YEAR(TODAY()),MONTH(TODAY()),E5), EDATE(DATE(YEAR(TODAY()),MONTH(TODAY()),E5),1) ) -> 46235 | G5: =IF(Subscriptions[[#This Row],[Renewal Frequency]]="Monthly", DATE( YEAR(DashBoard!$B$4), MONTH(DashBoard!$B$4), MIN(Subscriptions[[#This Row],[Renewal Date]],DAY(EOMONTH(DashBoard!$B$4,0))) ), DATE( YEAR(DashBoard!$B$4), MONTH(Subscriptions[[#This Row],[Renewal Date]]), DAY(Subscriptions[[#This Row],[Renewal Date]]) ) ) -> 46204 | H5: 3.99 until December 1st 2026 | J5: =MONTH(DashBoard!$B$4) -> 7
A6: Amazon Prime | B6: Miscellaneous | C6: 147.34 | D6: Annual | E6: 46107 | F6: =IF( DATE(YEAR(TODAY()),MONTH(E6),DAY(E6))>=TODAY(), DATE(YEAR(TODAY()),MONTH(E6),DAY(E6)), DATE(YEAR(TODAY())+1,MONTH(E6),DAY(E6)) ) -> 46472 | G6: =IF(Subscriptions[[#This Row],[Renewal Frequency]]="Monthly", DATE( YEAR(DashBoard!$B$4), MONTH(DashBoard!$B$4), MIN(Subscriptions[[#This Row],[Renewal Date]],DAY(EOMONTH(DashBoard!$B$4,0))) ), DATE( YEAR(DashBoard!$B$4), MONTH(Subscriptions[[#This Row],[Renewal Date]]), DAY(Subscriptions[[#This Row],[Renewal Date]]) ) ) -> 46107 | J6: =YEAR(DashBoard!$B$4) -> 2026
A7: Calm | B7: Healthcare | C7: 84.79 | D7: Annual | E7: 46386 | F7: =IF( DATE(YEAR(TODAY()),MONTH(E7),DAY(E7))>=TODAY(), DATE(YEAR(TODAY()),MONTH(E7),DAY(E7)), DATE(YEAR(TODAY())+1,MONTH(E7),DAY(E7)) ) -> 46386 | G7: =IF(Subscriptions[[#This Row],[Renewal Frequency]]="Monthly", DATE( YEAR(DashBoard!$B$4), MONTH(DashBoard!$B$4), MIN(Subscriptions[[#This Row],[Renewal Date]],DAY(EOMONTH(DashBoard!$B$4,0))) ), DATE( YEAR(DashBoard!$B$4), MONTH(Subscriptions[[#This Row],[Renewal Date]]), DAY(Subscriptions[[#This Row],[Renewal Date]]) ) ) -> 46386 | J7: =DATE(YEAR(DashBoard!$B$4),MONTH(DashBoard!$B$4),10) -> 46213
A8: Seeking Alpha | B8: Education | C8: 316.94 | D8: Annual | E8: 46246 | F8: =IF( DATE(YEAR(TODAY()),MONTH(E8),DAY(E8))>=TODAY(), DATE(YEAR(TODAY()),MONTH(E8),DAY(E8)), DATE(YEAR(TODAY())+1,MONTH(E8),DAY(E8)) ) -> 46246 | G8: =IF(Subscriptions[[#This Row],[Renewal Frequency]]="Monthly", DATE( YEAR(DashBoard!$B$4), MONTH(DashBoard!$B$4), MIN(Subscriptions[[#This Row],[Renewal Date]],DAY(EOMONTH(DashBoard!$B$4,0))) ), DATE( YEAR(DashBoard!$B$4), MONTH(Subscriptions[[#This Row],[Renewal Date]]), DAY(Subscriptions[[#This Row],[Renewal Date]]) ) ) -> 46246

Sheet Monthly Summary Sheet
A1: Month | B1: Salary Income | C1: Other Income | D1: Income | E1: Expense | F1: Subscriptions | G1: Expenses | H1: Savings | I1: Savings Rate
A2: 46204 | B2: =SUMIFS(Tracker[[Amount ]],Tracker[Type],B$1,Tracker[Date],">="&EOMONTH($A2,-1)+1,Tracker[Date],"<="&EOMONTH($A2,0)) -> 2347.51 | C2: =SUMIFS(Tracker[[Amount ]],Tracker[Type],C$1,Tracker[Date],">="&EOMONTH($A2,-1)+1,Tracker[Date],"<="&EOMONTH($A2,0)) -> 7.05 | D2: =SUM(Table6[[#This Row],[Salary Income]:[Other Income]]) -> 2354.56 | E2: =SUMIFS(Tracker[[Amount ]],Tracker[Type],E$1,Tracker[Date],">="&EOMONTH($A2,-1)+1,Tracker[Date],"<="&EOMONTH($A2,0)) -> 759.09 | F2: =SUMIFS( Subscriptions[Monthly Cost], Subscriptions[Period Renewal Date],">="&EOMONTH(A2,-1)+1, Subscriptions[Period Renewal Date],"<"&EOMONTH(A2,0)+1 ) -> 43.98 | G2: =Table6[[#This Row],[Expense]]+Table6[[#This Row],[Subscriptions]] -> 803.07 | H2: =MAX(Table6[[#This Row],[Income]]-Table6[[#This Row],[Expenses]],0) -> 1551.49 | I2: =IFERROR(Table6[[#This Row],[Savings]]/Table6[[#This Row],[Income]],0) -> 0.65892991
A3: 46235 | B3: =SUMIFS(Tracker[[Amount ]],Tracker[Type],B$1,Tracker[Date],">="&EOMONTH($A3,-1)+1,Tracker[Date],"<="&EOMONTH($A3,0)) -> 0 | C3: =SUMIFS(Tracker[[Amount ]],Tracker[Type],C$1,Tracker[Date],">="&EOMONTH($A3,-1)+1,Tracker[Date],"<="&EOMONTH($A3,0)) -> 0 | D3: =SUM(Table6[[#This Row],[Salary Income]:[Other Income]]) -> 0 | E3: =SUMIFS(Tracker[[Amount ]],Tracker[Type],E$1,Tracker[Date],">="&EOMONTH($A3,-1)+1,Tracker[Date],"<="&EOMONTH($A3,0)) -> 0 | F3: =SUMIFS( Subscriptions[Monthly Cost], Subscriptions[Period Renewal Date],">="&EOMONTH(A3,-1)+1, Subscriptions[Period Renewal Date],"<"&EOMONTH(A3,0)+1 ) -> 316.94 | G3: =Table6[[#This Row],[Expense]]+Table6[[#This Row],[Subscriptions]] -> 316.94 | H3: =MAX(Table6[[#This Row],[Income]]-Table6[[#This Row],[Expenses]],0) -> 0 | I3: =IFERROR(Table6[[#This Row],[Savings]]/Table6[[#This Row],[Income]],0) -> 0

Sheet Charts Sheet
A1: Filtered Expenses
A3: Donut Chart | D3: Bar Chart | K3: Donut Chart
A4: {=_xlfn._xlws.SORT(_xlfn._xlws.FILTER(_xlfn.CHOOSECOLS(DashBoard!A15:C25, 1, 3), DashBoard!C15:C25), 2, -1)} -> Utilities | B4: 200 | D4: {=_xlfn._xlws.FILTER(DashBoard!A15:E25,(DashBoard!C15:C25>0)+(DashBoard!D15:D25>0))} -> Housing | E4: 0 | F4: 100 | G4: 0 | H4: -100 | I4: =ABS(H4) -> 100 | K4: {=_xlfn._xlws.SORT(_xlfn.CHOOSECOLS(DashBoard!A30:C32,1,3),2,-1)} -> Debt Paydown | L4: 930.894
A5: Leisure | B5: 131 | D5: Utilities | E5: 0 | F5: 200 | G5: 0 | H5: -200 | I5: =ABS(H5) -> 200 | K5: Emeregency Fund | L5: 310.298
A6: Debt | B6: 130 | D6: Transportation | E6: 0 | F6: 26.54 | G6: 500 | H6: 473.46 | I6: =ABS(H6) -> 473.46 | K6: Investments | L6: 310.298
A7: Insurance | B7: 120 | D7: Insurance | E7: 0 | F7: 120 | G7: 120 | H7: 0 | I7: =ABS(H7) -> 0
A8: Housing | B8: 100 | D8: Groceries | E8: 0 | F8: 6.99 | G8: 100 | H8: 93.01 | I8: =ABS(H8) -> 93.01
A9: Subscriptions | B9: 43.98 | D9: Leisure | E9: 0 | F9: 131 | G9: 200 | H9: 69 | I9: =ABS(H9) -> 69
A10: Miscellaneous | B10: 34.56 | D10: Healthcare | E10: 0 | F10: 5 | G10: 50 | H10: 45 | I10: =ABS(H10) -> 45
A11: Transportation | B11: 26.54 | D11: Debt | E11: 0 | F11: 130 | G11: 800 | H11: 670 | I11: =ABS(H11) -> 670
A12: Groceries | B12: 6.99 | D12: Education | E12: 0 | F12: 5 | G12: 20 | H12: 15 | I12: =ABS(H12) -> 15
A13: Healthcare | B13: 5 | D13: Subscriptions | E13: 0 | F13: 43.98 | G13: 40 | H13: -3.98 | I13: =ABS(H13) -> 3.98
A14: Education | B14: 5 | D14: Miscellaneous | E14: 0 | F14: 34.56 | G14: 50 | H14: 15.44 | I14: =ABS(H14) -> 15.44
D16: {=_xlfn._xlws.SORT(D4:I14,6,-1)} -> Debt | E16: 0 | F16: 130 | G16: 800 | H16: 670 | I16: 670
D17: Transportation | E17: 0 | F17: 26.54 | G17: 500 | H17: 473.46 | I17: 473.46
D18: Utilities | E18: 0 | F18: 200 | G18: 0 | H18: -200 | I18: 200
D19: Housing | E19: 0 | F19: 100 | G19: 0 | H19: -100 | I19: 100
D20: Groceries | E20: 0 | F20: 6.99 | G20: 100 | H20: 93.01 | I20: 93.01
D21: Leisure | E21: 0 | F21: 131 | G21: 200 | H21: 69 | I21: 69
D22: Healthcare | E22: 0 | F22: 5 | G22: 50 | H22: 45 | I22: 45
D23: Miscellaneous | E23: 0 | F23: 34.56 | G23: 50 | H23: 15.44 | I23: 15.44
D24: Education | E24: 0 | F24: 5 | G24: 20 | H24: 15 | I24: 15
D25: Subscriptions | E25: 0 | F25: 43.98 | G25: 40 | H25: -3.98 | I25: 3.98
D26: Insurance | E26: 0 | F26: 120 | G26: 120 | H26: 0 | I26: 0
E27: Actual | F27: Budget
D28: {=_xlfn.CHOOSECOLS(_xlfn._xlws.SORT(D4:I14,6,-1),1,3,4)} -> Debt | E28: 130 | F28: 800
D29: Transportation | E29: 26.54 | F29: 500
D30: Utilities | E30: 200 | F30: 0
D31: Housing | E31: 100 | F31: 0
D32: Groceries | E32: 6.99 | F32: 100
D33: Leisure | E33: 131 | F33: 200
D34: Healthcare | E34: 5 | F34: 50
D35: Miscellaneous | E35: 34.56 | F35: 50
D36: Education | E36: 5 | F36: 20
D37: Subscriptions | E37: 43.98 | F37: 40
D38: Insurance | E38: 120 | F38: 120
